__init__.py
crew_python_runner.py
crew_python_runner-0.2.1.dist-info/LICENSE
crew_python_runner-0.2.1.dist-info/METADATA
crew_python_runner-0.2.1.dist-info/WHEEL
crew_python_runner-0.2.1.dist-info/top_level.txt
crew_python_runner-0.2.1.dist-info/RECORD
