Metadata-Version: 2.1
Name: crew_python_runner
Version: 0.2.1
Summary: Package to run crew.ai generated code in a docker instance
Author-email: Chris Handy <maximinus@gmail.com>
Project-URL: Homepage, https://github.com/maximinus/crew-python-runner
Project-URL: Issues, https://github.com/maximinus/crew-python-runner/issues
Classifier: Programming Language :: Python :: 3
Classifier: Development Status :: 4 - Beta
Classifier: License :: OSI Approved :: Apache Software License
Classifier: Operating System :: OS Independent
Requires-Python: >=3.11
License-File: LICENSE
Requires-Dist: docker >=7.0.0
Requires-Dist: crewai[tools]
